coland/__init__.py
coland/clitools/__init__.py
coland/clitools/cli.py
coland-0.0.0.1.dist-info/LICENSE
coland-0.0.0.1.dist-info/METADATA
coland-0.0.0.1.dist-info/WHEEL
coland-0.0.0.1.dist-info/entry_points.txt
coland-0.0.0.1.dist-info/top_level.txt
coland-0.0.0.1.dist-info/RECORD
