Metadata-Version: 2.1
Name: coland
Version: 0.0.0.1
Summary: Cloud python code library.
Home-page: https://gitee.com/peiiii/coland
Author: Wang Pei
Author-email: 1535376447@qq.com
License: UNKNOWN
Platform: UNKNOWN
Classifier: Programming Language :: Python :: 3
Classifier: License :: OSI Approved :: MIT License
Classifier: Operating System :: OS Independent
Requires-Python: >=3.0
Requires-Dist: jinja2
Requires-Dist: fire
